tlds/__init__.py
tlds/_data.py
tlds-2025102200.dist-info/LICENSE
tlds-2025102200.dist-info/METADATA
tlds-2025102200.dist-info/WHEEL
tlds-2025102200.dist-info/top_level.txt
tlds-2025102200.dist-info/zip-safe
tlds-2025102200.dist-info/RECORD
