Metadata-Version: 2.1
Name: tlds
Version: 2025102200
Summary: Automatically updated list of valid TLDs taken directly from IANA
Home-page: https://github.com/kichik/tlds
Author: Amir Szekely
Author-email: kichik@gmail.com
License: MIT
Keywords: tld
Classifier: Development Status :: 5 - Production/Stable
Classifier: Programming Language :: Python
Classifier: License :: OSI Approved :: MIT License
Classifier: Topic :: Communications
License-File: LICENSE
